curvesim/__init__.py
curvesim/__main__.py
curvesim/constants.py
curvesim/logging.py
curvesim/version.py
curvesim/_order_book/__init__.py
curvesim/exceptions/__init__.py
curvesim/iterators/__init__.py
curvesim/iterators/param_samplers/__init__.py
curvesim/iterators/param_samplers/parameterized_pool_iterator.py
curvesim/iterators/param_samplers/pool_mixins.py
curvesim/iterators/price_samplers/__init__.py
curvesim/iterators/price_samplers/price_volume.py
curvesim/metrics/__init__.py
curvesim/metrics/base.py
curvesim/metrics/metrics.py
curvesim/metrics/results/__init__.py
curvesim/metrics/results/make_results.py
curvesim/metrics/results/sim_results.py
curvesim/metrics/state_log/__init__.py
curvesim/metrics/state_log/log.py
curvesim/metrics/state_log/pool_parameters.py
curvesim/metrics/state_log/pool_state.py
curvesim/network/__init__.py
curvesim/network/coingecko.py
curvesim/network/curve_prices.py
curvesim/network/http.py
curvesim/network/subgraph.py
curvesim/network/utils.py
curvesim/network/web3.py
curvesim/overrides/__init__.py
curvesim/pipelines/__init__.py
curvesim/pipelines/common/__init__.py
curvesim/pipelines/simple/__init__.py
curvesim/pipelines/simple/__main__.py
curvesim/pipelines/simple/strategy.py
curvesim/pipelines/simple/trader.py
curvesim/pipelines/vol_limited_arb/__init__.py
curvesim/pipelines/vol_limited_arb/strategy.py
curvesim/pipelines/vol_limited_arb/trader.py
curvesim/plot/__init__.py
curvesim/plot/result_plotter.py
curvesim/plot/altair/__init__.py
curvesim/plot/altair/chart_properties.py
curvesim/plot/altair/make_chart.py
curvesim/plot/altair/selectors.py
curvesim/plot/altair/styles.py
curvesim/plot/altair/results/__init__.py
curvesim/plot/altair/results/make_page.py
curvesim/plot/altair/results/preprocessing.py
curvesim/plot/altair/results/result_plotter.py
curvesim/plot/altair/results/result_selectors.py
curvesim/plot/altair/results/tooltip.py
curvesim/pool/__init__.py
curvesim/pool/base.py
curvesim/pool/snapshot.py
curvesim-0.5.0.dist-info/LICENSE.md
curvesim-0.5.0.dist-info/METADATA
curvesim-0.5.0.dist-info/WHEEL
curvesim-0.5.0.dist-info/top_level.txt
curvesim-0.5.0.dist-info/RECORD
