Metadata-Version: 2.1
Name: curvesim
Version: 0.5.0
Summary: Simulate Curve pools
Home-page: https://github.com/curveresearch/curvesim
Author: Curve Research
Author-email: help@curveresearch.org
License: MIT
Project-URL: Documentation, https://curvesim.readthedocs.io
Project-URL: Source, https://github.com/curveresearch/curvesim
Project-URL: Tracker, https://github.com/curveresearch/curvesim/issues
Classifier: Development Status :: 4 - Beta
Classifier: Environment :: Console
Classifier: Intended Audience :: Science/Research
Classifier: Intended Audience :: Developers
Classifier: Intended Audience :: Financial and Insurance Industry
Classifier: License :: OSI Approved :: MIT License
Classifier: Natural Language :: English
Classifier: Operating System :: OS Independent
Classifier: Programming Language :: Python :: 3.8
Classifier: Programming Language :: Python :: 3.9
Classifier: Programming Language :: Python :: 3.10
Classifier: Programming Language :: Python :: 3.11
Requires-Python: >=3.8
License-File: LICENSE.md
Requires-Dist: numpy>=1.23.4
Requires-Dist: pandas>=1.5.1
Requires-Dist: scipy!=1.11.2,>=1.9.3
Requires-Dist: gmpy2>=2.1.2
Requires-Dist: matplotlib>=3.5.3
Requires-Dist: web3>=6.0.0b4
Requires-Dist: requests>=2.28.1
Requires-Dist: tenacity>=8.1.0
Requires-Dist: python-dotenv>=0.21.0
Requires-Dist: altair>=5.0.0
